dbdk/__init__.py
dbdk/kit.py
dbdk/main.py
dbdk/test.py
dbdk/kit_modules/__init__.py
dbdk/kit_modules/cogs.py
dbdk/kit_modules/components.py
dbdk/kit_modules/embed.py
dbdk/kit_modules/interaction_control.py
dbdk/kit_modules/modal.py
dbdk/kit_modules/root.py
dbdk/kit_modules/states.py
dbdk/kit_modules/types.py
dbdk/kit_modules/utils.py
dbdk/kit_modules/view.py
dbdk-1.2.dist-info/METADATA
dbdk-1.2.dist-info/WHEEL
dbdk-1.2.dist-info/top_level.txt
dbdk-1.2.dist-info/RECORD
