Metadata-Version: 2.1
Name: dbdk
Version: 1.2
Summary: Discord Bot Dev Kit is a set of funtions and classes to simplify the creation of discord bots
Home-page: 
Author: Hendrick Y. "NoVa
Author-email: hendrickrodriguez.nova@gmail.com
License: MIT
Requires-Dist: py-cord
Requires-Dist: datetime
